README.md
setup.py
ribo_torch/__init__.py
ribo_torch/classifier.py
ribo_torch/utility.py
ribo_torch.egg-info/PKG-INFO
ribo_torch.egg-info/SOURCES.txt
ribo_torch.egg-info/dependency_links.txt
ribo_torch.egg-info/not-zip-safe
ribo_torch.egg-info/top_level.txt