Metadata-Version: 1.0
Name: ribo-torch
Version: 0.2
Summary: a package for creating, training and predecting using torchvision models
Home-page: UNKNOWN
Author: Ahmed Gharib
Author-email: a.gharib89@yahoo.com
License: UNKNOWN
Platform: UNKNOWN
